config_precedence/__init__.py
config_precedence/config_option.py
config_precedence/config_precedence.py
config_precedence-1.0.0.dist-info/METADATA
config_precedence-1.0.0.dist-info/WHEEL
config_precedence-1.0.0.dist-info/top_level.txt
config_precedence-1.0.0.dist-info/RECORD
