Metadata-Version: 2.1
Name: config-precedence
Version: 1.0.0
Summary: Define the order of precedence of a list of configuration options
Home-page: UNKNOWN
Author: Eddy Mwenda
Author-email: mwendaeddy@gmail.com
License: UNKNOWN
Platform: UNKNOWN
Requires-Python: >=3.7
